prioritized_methods.py
setup.cfg
setup.py
prioritized_methods.egg-info/PKG-INFO
prioritized_methods.egg-info/SOURCES.txt
prioritized_methods.egg-info/dependency_links.txt
prioritized_methods.egg-info/requires.txt
prioritized_methods.egg-info/top_level.txt
prioritized_methods.egg-info/zip-safe
