Metadata-Version: 1.0
Name: prioritized_methods
Version: 0.2
Summary: An extension to PEAK-Rules to prioritize methods in order to to avoid AmbiguousMethods situations
Home-page: UNKNOWN
Author: Alberto Valverde Gonzalez
Author-email: alberto@toscat.net
License: MIT
Download-URL: http://toscawidgets.org/download
Keywords: PEAK rules generic functions dispatch
Platform: UNKNOWN
